{
	"project_name" : "project_1",
	"commit_hash" : "",
	"UTC" : "",
	"objects" : 	{
		"vrbox_10" : 		{
			"max_class" : "vr-box",
			"text" : "vrbox_10",
			"var_name" : "vrbox_10",
			"vr_position" : [ 0.1287, 0.4711, 0.0762 ],
			"patcher_position" : [ 20, 250 ]
		}
,
		"vrbox_0" : 		{
			"max_class" : "vr-box",
			"text" : "vrbox_0",
			"var_name" : "vrbox_0",
			"vr_position" : [ 0.1092, 0.7855, 0.0212 ],
			"patcher_position" : [ 20, 0 ]
		}
,
		"vrbox_1" : 		{
			"max_class" : "vr-box",
			"text" : "vrbox_1",
			"var_name" : "vrbox_1",
			"vr_position" : [ 0.8529, 0.3584, 0.1617 ],
			"patcher_position" : [ 20, 25 ]
		}
,
		"vrbox_2" : 		{
			"max_class" : "vr-box",
			"text" : "vrbox_2",
			"var_name" : "vrbox_2",
			"vr_position" : [ 0.6936, 0.9224, 0.6136 ],
			"patcher_position" : [ 20, 50 ]
		}
,
		"vrbox_3" : 		{
			"max_class" : "vr-box",
			"text" : "vrbox_3",
			"var_name" : "vrbox_3",
			"vr_position" : [ 0.3419, 0.6597, 0.5316 ],
			"patcher_position" : [ 20, 75 ]
		}
,
		"vrbox_4" : 		{
			"max_class" : "vr-box",
			"text" : "vrbox_4",
			"var_name" : "vrbox_4",
			"vr_position" : [ 0.7331, 0.1664, 0.6769 ],
			"patcher_position" : [ 20, 100 ]
		}
,
		"vrbox_5" : 		{
			"max_class" : "vr-box",
			"text" : "vrbox_5",
			"var_name" : "vrbox_5",
			"vr_position" : [ 0.9896, 0.9998, 0.6877 ],
			"patcher_position" : [ 20, 125 ]
		}
,
		"vrbox_6" : 		{
			"max_class" : "vr-box",
			"text" : "vrbox_6",
			"var_name" : "vrbox_6",
			"vr_position" : [ 0.4747, 0.4263, 0.2588 ],
			"patcher_position" : [ 20, 150 ]
		}
,
		"vrbox_7" : 		{
			"max_class" : "vr-box",
			"text" : "vrbox_7",
			"var_name" : "vrbox_7",
			"vr_position" : [ 0.9981, 0.4338, 0.4429 ],
			"patcher_position" : [ 20, 175 ]
		}
,
		"vrbox_8" : 		{
			"max_class" : "vr-box",
			"text" : "vrbox_8",
			"var_name" : "vrbox_8",
			"vr_position" : [ 0.5137, 0.9266, 0.5106 ],
			"patcher_position" : [ 20, 200 ]
		}
,
		"vrbox_9" : 		{
			"max_class" : "vr-box",
			"text" : "vrbox_9",
			"var_name" : "vrbox_9",
			"vr_position" : [ 0.9822, 0.3006, 0.7759 ],
			"patcher_position" : [ 20, 225 ]
		}

	}

}
