{
	"project_name" : "project_1",
	"commit_hash" : "",
	"UTC" : "",
	"objects" : 	{
		"vrbox_0" : 		{
			"max_class" : "vr-box",
			"text" : "vrbox_0",
			"var_name" : "vrbox_0",
			"vr_position" : [ 0.9503, 0.5448, 0.5254 ],
			"patcher_position" : [ 20, 0 ]
		}
,
		"vrbox_1" : 		{
			"max_class" : "vr-box",
			"text" : "vrbox_1",
			"var_name" : "vrbox_1",
			"vr_position" : [ 0.5534, 0.0258, 0.9299 ],
			"patcher_position" : [ 20, 25 ]
		}
,
		"vrbox_2" : 		{
			"max_class" : "vr-box",
			"text" : "vrbox_2",
			"var_name" : "vrbox_2",
			"vr_position" : [ 0.8649, 0.5817, 0.9296 ],
			"patcher_position" : [ 20, 50 ]
		}
,
		"vrbox_3" : 		{
			"max_class" : "vr-box",
			"text" : "vrbox_3",
			"var_name" : "vrbox_3",
			"vr_position" : [ 0.265, 0.9623, 0.1033 ],
			"patcher_position" : [ 20, 75 ]
		}
,
		"vrbox_4" : 		{
			"max_class" : "vr-box",
			"text" : "vrbox_4",
			"var_name" : "vrbox_4",
			"vr_position" : [ 0.6415, 0.9698, 0.0156 ],
			"patcher_position" : [ 20, 100 ]
		}
,
		"vrbox_5" : 		{
			"max_class" : "vr-box",
			"text" : "vrbox_5",
			"var_name" : "vrbox_5",
			"vr_position" : [ 0.3413, 0.5325, 0.0624 ],
			"patcher_position" : [ 20, 125 ]
		}
,
		"vrbox_6" : 		{
			"max_class" : "vr-box",
			"text" : "vrbox_6",
			"var_name" : "vrbox_6",
			"vr_position" : [ 0.5804, 0.0874, 0.0956 ],
			"patcher_position" : [ 20, 150 ]
		}
,
		"vrbox_7" : 		{
			"max_class" : "vr-box",
			"text" : "vrbox_7",
			"var_name" : "vrbox_7",
			"vr_position" : [ 0.0409, 0.8318, 0.1277 ],
			"patcher_position" : [ 20, 175 ]
		}
,
		"vrbox_8" : 		{
			"max_class" : "vr-box",
			"text" : "vrbox_8",
			"var_name" : "vrbox_8"
		}

	}

}
