{
	"project_name" : "project_1",
	"commit_hash" : "",
	"UTC" : "",
	"objects" : 	{
		"vrbox_0" : 		{
			"max_class" : "vr-box",
			"text" : "vrbox_0",
			"var_name" : "vrbox_0",
			"vr_position" : [ 0.5161, 0.0218, 0.6032 ],
			"patcher_position" : [ 20, 0 ]
		}
,
		"vrbox_1" : 		{
			"max_class" : "vr-box",
			"text" : "vrbox_1",
			"var_name" : "vrbox_1",
			"vr_position" : [ 0.1342, 0.632, 0.8182 ],
			"patcher_position" : [ 20, 25 ]
		}
,
		"vrbox_2" : 		{
			"max_class" : "vr-box",
			"text" : "vrbox_2",
			"var_name" : "vrbox_2",
			"vr_position" : [ 0.3145, 0.7604, 0.6604 ],
			"patcher_position" : [ 20, 50 ]
		}
,
		"vrbox_3" : 		{
			"max_class" : "vr-box",
			"text" : "vrbox_3",
			"var_name" : "vrbox_3",
			"vr_position" : [ 0.0202, 0.9549, 0.2463 ],
			"patcher_position" : [ 20, 75 ]
		}
,
		"vrbox_4" : 		{
			"max_class" : "vr-box",
			"text" : "vrbox_4",
			"var_name" : "vrbox_4",
			"vr_position" : [ 0.7679, 0.9137, 0.6472 ],
			"patcher_position" : [ 20, 100 ]
		}

	}

}
